{"nodes": [{"id": "d_dev_open_vayra_cities_apps_web_src_domain_types_stop_ts", "label": "stop.ts", "file_type": "code", "source_file": "D:\\__DEV\\open-vayra-cities\\apps\\web\\src\\domain\\types\\stop.ts", "source_location": "L1"}, {"id": "types_stop_createstopid", "label": "createStopId()", "file_type": "code", "source_file": "D:\\__DEV\\open-vayra-cities\\apps\\web\\src\\domain\\types\\stop.ts", "source_location": "L26"}], "edges": [{"source": "d_dev_open_vayra_cities_apps_web_src_domain_types_stop_ts", "target": "types_stop_createstopid", "relation": "contains", "confidence": "EXTRACTED", "source_file": "D:\\__DEV\\open-vayra-cities\\apps\\web\\src\\domain\\types\\stop.ts", "source_location": "L26", "weight": 1.0}], "raw_calls": []}