{"nodes": [{"id": "d_dev_open_vayra_cities_scripts_scenario_demand_prepare_osm_attractors_source_ps1", "label": "prepare-osm-attractors-source.ps1", "file_type": "code", "source_file": "D:\\__DEV\\open-vayra-cities\\scripts\\scenario-demand\\prepare-osm-attractors-source.ps1", "source_location": "L1"}, {"id": "scenario_demand_prepare_osm_attractors_source_get_containerpath", "label": "Get-ContainerPath()", "file_type": "code", "source_file": "D:\\__DEV\\open-vayra-cities\\scripts\\scenario-demand\\prepare-osm-attractors-source.ps1", "source_location": "L106"}], "edges": [{"source": "d_dev_open_vayra_cities_scripts_scenario_demand_prepare_osm_attractors_source_ps1", "target": "scenario_demand_prepare_osm_attractors_source_get_containerpath", "relation": "contains", "confidence": "EXTRACTED", "source_file": "D:\\__DEV\\open-vayra-cities\\scripts\\scenario-demand\\prepare-osm-attractors-source.ps1", "source_location": "L106", "weight": 1.0}], "raw_calls": [{"caller_nid": "scenario_demand_prepare_osm_attractors_source_get_containerpath", "callee": "Write-Error", "is_member_call": false, "source_file": "D:\\__DEV\\open-vayra-cities\\scripts\\scenario-demand\\prepare-osm-attractors-source.ps1", "source_location": "L113"}]}